langextract_openai/__init__.py
langextract_openai/openai_providers.py
langextract_openai-0.0.2.dist-info/licenses/LICENSE
langextract_openai-0.0.2.dist-info/METADATA
langextract_openai-0.0.2.dist-info/WHEEL
langextract_openai-0.0.2.dist-info/entry_points.txt
langextract_openai-0.0.2.dist-info/top_level.txt
langextract_openai-0.0.2.dist-info/RECORD
