Metadata-Version: 2.4
Name: langextract-openai
Version: 0.0.2
Summary: OpenAI and Azure OpenAI provider plugin for LangExtract
License: Apache-2.0
Classifier: License :: OSI Approved :: Apache Software License
Classifier: Programming Language :: Python
Classifier: Programming Language :: Python :: 3
Classifier: Programming Language :: Python :: 3 :: Only
Requires-Python: >=3.10
License-File: LICENSE
Requires-Dist: langextract
Requires-Dist: openai>=1.35.0
Dynamic: license-file
